{
  "tableName": "tab_BoardMapping",
  "description": "Mapping for boards",
  "restrictionTypeId": "Public",
  "isInputUnique": true,
  "groupName": "Materials",
  "columns": [
    {
      "name": "_id",
      "type": "Integer",
      "allowNull": false
    },
    {
      "name": "in_NeutralColor",
      "type": "Text",
      "allowNull": true
    },
    {
      "name": "in_BoardThkMin",
      "type": "Dim",
      "allowNull": false
    },
    {
      "name": "in_BoardThkMax",
      "type": "Dim",
      "allowNull": false
    },
    {
      "name": "BoardId",
      "type": "Text",
      "allowNull": true
    }
  ],
  "rows": [
    {
      "data": [
        {
          "columnName": "in_NeutralColor",
          "value": "152"
        },
        {
          "columnName": "in_BoardThkMin",
          "value": "30"
        },
        {
          "columnName": "in_BoardThkMax",
          "value": "99"
        },
        {
          "columnName": "BoardId",
          "value": "U502ST9_38"
        }
      ]
    },
    {
      "data": [
        {
          "columnName": "in_NeutralColor",
          "value": "152"
        },
        {
          "columnName": "in_BoardThkMin",
          "value": "7"
        },
        {
          "columnName": "in_BoardThkMax",
          "value": "9"
        },
        {
          "columnName": "BoardId",
          "value": "U502ST9_8"
        }
      ]
    },
    {
      "data": [
        {
          "columnName": "in_NeutralColor",
          "value": "152"
        },
        {
          "columnName": "in_BoardThkMin",
          "value": "15"
        },
        {
          "columnName": "in_BoardThkMax",
          "value": "17"
        },
        {
          "columnName": "BoardId",
          "value": "U502ST9_16"
        }
      ]
    },
    {
      "data": [
        {
          "columnName": "in_NeutralColor",
          "value": "152"
        },
        {
          "columnName": "in_BoardThkMin",
          "value": "18"
        },
        {
          "columnName": "in_BoardThkMax",
          "value": "20"
        },
        {
          "columnName": "BoardId",
          "value": "U502ST9_19"
        }
      ]
    },
    {
      "data": [
        {
          "columnName": "in_NeutralColor",
          "value": "152"
        },
        {
          "columnName": "in_BoardThkMin",
          "value": "20"
        },
        {
          "columnName": "in_BoardThkMax",
          "value": "30"
        },
        {
          "columnName": "BoardId",
          "value": "U502ST9_25"
        }
      ]
    },
    {
      "data": [
        {
          "columnName": "in_NeutralColor",
          "value": "155"
        },
        {
          "columnName": "in_BoardThkMin",
          "value": "20"
        },
        {
          "columnName": "in_BoardThkMax",
          "value": "30"
        },
        {
          "columnName": "BoardId",
          "value": "U575ST9_25"
        }
      ]
    },
    {
      "data": [
        {
          "columnName": "in_NeutralColor",
          "value": "155"
        },
        {
          "columnName": "in_BoardThkMin",
          "value": "15"
        },
        {
          "columnName": "in_BoardThkMax",
          "value": "17"
        },
        {
          "columnName": "BoardId",
          "value": "U575ST9_16"
        }
      ]
    },
    {
      "data": [
        {
          "columnName": "in_NeutralColor",
          "value": "155"
        },
        {
          "columnName": "in_BoardThkMin",
          "value": "7"
        },
        {
          "columnName": "in_BoardThkMax",
          "value": "9"
        },
        {
          "columnName": "BoardId",
          "value": "U575ST9_8"
        }
      ]
    },
    {
      "data": [
        {
          "columnName": "in_NeutralColor",
          "value": "155"
        },
        {
          "columnName": "in_BoardThkMin",
          "value": "30"
        },
        {
          "columnName": "in_BoardThkMax",
          "value": "99"
        },
        {
          "columnName": "BoardId",
          "value": "U575ST9_38"
        }
      ]
    },
    {
      "data": [
        {
          "columnName": "in_NeutralColor",
          "value": "155"
        },
        {
          "columnName": "in_BoardThkMin",
          "value": "18"
        },
        {
          "columnName": "in_BoardThkMax",
          "value": "20"
        },
        {
          "columnName": "BoardId",
          "value": "U575ST9_19"
        }
      ]
    },
    {
      "data": [
        {
          "columnName": "in_NeutralColor",
          "value": "160"
        },
        {
          "columnName": "in_BoardThkMin",
          "value": "30"
        },
        {
          "columnName": "in_BoardThkMax",
          "value": "99"
        },
        {
          "columnName": "BoardId",
          "value": "U640ST9_38"
        }
      ]
    },
    {
      "data": [
        {
          "columnName": "in_NeutralColor",
          "value": "160"
        },
        {
          "columnName": "in_BoardThkMin",
          "value": "7"
        },
        {
          "columnName": "in_BoardThkMax",
          "value": "9"
        },
        {
          "columnName": "BoardId",
          "value": "U640ST9_8"
        }
      ]
    },
    {
      "data": [
        {
          "columnName": "in_NeutralColor",
          "value": "160"
        },
        {
          "columnName": "in_BoardThkMin",
          "value": "15"
        },
        {
          "columnName": "in_BoardThkMax",
          "value": "17"
        },
        {
          "columnName": "BoardId",
          "value": "U640ST9_16"
        }
      ]
    },
    {
      "data": [
        {
          "columnName": "in_NeutralColor",
          "value": "160"
        },
        {
          "columnName": "in_BoardThkMin",
          "value": "20"
        },
        {
          "columnName": "in_BoardThkMax",
          "value": "30"
        },
        {
          "columnName": "BoardId",
          "value": "U640ST9_25"
        }
      ]
    },
    {
      "data": [
        {
          "columnName": "in_NeutralColor",
          "value": "160"
        },
        {
          "columnName": "in_BoardThkMin",
          "value": "18"
        },
        {
          "columnName": "in_BoardThkMax",
          "value": "20"
        },
        {
          "columnName": "BoardId",
          "value": "U640ST9_19"
        }
      ]
    },
    {
      "data": [
        {
          "columnName": "in_NeutralColor",
          "value": "165"
        },
        {
          "columnName": "in_BoardThkMin",
          "value": "18"
        },
        {
          "columnName": "in_BoardThkMax",
          "value": "20"
        },
        {
          "columnName": "BoardId",
          "value": "U645ST9_19"
        }
      ]
    },
    {
      "data": [
        {
          "columnName": "in_NeutralColor",
          "value": "165"
        },
        {
          "columnName": "in_BoardThkMin",
          "value": "15"
        },
        {
          "columnName": "in_BoardThkMax",
          "value": "17"
        },
        {
          "columnName": "BoardId",
          "value": "U645ST9_16"
        }
      ]
    },
    {
      "data": [
        {
          "columnName": "in_NeutralColor",
          "value": "165"
        },
        {
          "columnName": "in_BoardThkMin",
          "value": "7"
        },
        {
          "columnName": "in_BoardThkMax",
          "value": "9"
        },
        {
          "columnName": "BoardId",
          "value": "U645ST9_8"
        }
      ]
    },
    {
      "data": [
        {
          "columnName": "in_NeutralColor",
          "value": "165"
        },
        {
          "columnName": "in_BoardThkMin",
          "value": "30"
        },
        {
          "columnName": "in_BoardThkMax",
          "value": "99"
        },
        {
          "columnName": "BoardId",
          "value": "U645ST9_38"
        }
      ]
    },
    {
      "data": [
        {
          "columnName": "in_NeutralColor",
          "value": "165"
        },
        {
          "columnName": "in_BoardThkMin",
          "value": "20"
        },
        {
          "columnName": "in_BoardThkMax",
          "value": "30"
        },
        {
          "columnName": "BoardId",
          "value": "U645ST9_25"
        }
      ]
    },
    {
      "data": [
        {
          "columnName": "in_NeutralColor",
          "value": "190"
        },
        {
          "columnName": "in_BoardThkMin",
          "value": "20"
        },
        {
          "columnName": "in_BoardThkMax",
          "value": "30"
        },
        {
          "columnName": "BoardId",
          "value": "W980ST7_25"
        }
      ]
    },
    {
      "data": [
        {
          "columnName": "in_NeutralColor",
          "value": "190"
        },
        {
          "columnName": "in_BoardThkMin",
          "value": "30"
        },
        {
          "columnName": "in_BoardThkMax",
          "value": "99"
        },
        {
          "columnName": "BoardId",
          "value": "W980ST7_38"
        }
      ]
    },
    {
      "data": [
        {
          "columnName": "in_NeutralColor",
          "value": "190"
        },
        {
          "columnName": "in_BoardThkMin",
          "value": "18"
        },
        {
          "columnName": "in_BoardThkMax",
          "value": "20"
        },
        {
          "columnName": "BoardId",
          "value": "W980ST7_19"
        }
      ]
    },
    {
      "data": [
        {
          "columnName": "in_NeutralColor",
          "value": "190"
        },
        {
          "columnName": "in_BoardThkMin",
          "value": "15"
        },
        {
          "columnName": "in_BoardThkMax",
          "value": "17"
        },
        {
          "columnName": "BoardId",
          "value": "W980ST7_16"
        }
      ]
    },
    {
      "data": [
        {
          "columnName": "in_NeutralColor",
          "value": "190"
        },
        {
          "columnName": "in_BoardThkMin",
          "value": "7"
        },
        {
          "columnName": "in_BoardThkMax",
          "value": "9"
        },
        {
          "columnName": "BoardId",
          "value": "W980ST7_8"
        }
      ]
    },
    {
      "data": [
        {
          "columnName": "in_NeutralColor",
          "value": "199"
        },
        {
          "columnName": "in_BoardThkMin",
          "value": "30"
        },
        {
          "columnName": "in_BoardThkMax",
          "value": "99"
        },
        {
          "columnName": "BoardId",
          "value": "U999ST7_38"
        }
      ]
    },
    {
      "data": [
        {
          "columnName": "in_NeutralColor",
          "value": "199"
        },
        {
          "columnName": "in_BoardThkMin",
          "value": "7"
        },
        {
          "columnName": "in_BoardThkMax",
          "value": "9"
        },
        {
          "columnName": "BoardId",
          "value": "U999ST7_8"
        }
      ]
    },
    {
      "data": [
        {
          "columnName": "in_NeutralColor",
          "value": "199"
        },
        {
          "columnName": "in_BoardThkMin",
          "value": "15"
        },
        {
          "columnName": "in_BoardThkMax",
          "value": "17"
        },
        {
          "columnName": "BoardId",
          "value": "U999ST7_16"
        }
      ]
    },
    {
      "data": [
        {
          "columnName": "in_NeutralColor",
          "value": "199"
        },
        {
          "columnName": "in_BoardThkMin",
          "value": "20"
        },
        {
          "columnName": "in_BoardThkMax",
          "value": "30"
        },
        {
          "columnName": "BoardId",
          "value": "U999ST7_19"
        }
      ]
    },
    {
      "data": [
        {
          "columnName": "in_NeutralColor",
          "value": "199"
        },
        {
          "columnName": "in_BoardThkMin",
          "value": "18"
        },
        {
          "columnName": "in_BoardThkMax",
          "value": "20"
        },
        {
          "columnName": "BoardId",
          "value": "U999ST7_19"
        }
      ]
    },
    {
      "data": [
        {
          "columnName": "in_NeutralColor",
          "value": "230"
        },
        {
          "columnName": "in_BoardThkMin",
          "value": "30"
        },
        {
          "columnName": "in_BoardThkMax",
          "value": "99"
        },
        {
          "columnName": "BoardId",
          "value": "H3860ST9_38"
        }
      ]
    },
    {
      "data": [
        {
          "columnName": "in_NeutralColor",
          "value": "230"
        },
        {
          "columnName": "in_BoardThkMin",
          "value": "15"
        },
        {
          "columnName": "in_BoardThkMax",
          "value": "17"
        },
        {
          "columnName": "BoardId",
          "value": "H3860ST9_16"
        }
      ]
    },
    {
      "data": [
        {
          "columnName": "in_NeutralColor",
          "value": "230"
        },
        {
          "columnName": "in_BoardThkMin",
          "value": "18"
        },
        {
          "columnName": "in_BoardThkMax",
          "value": "20"
        },
        {
          "columnName": "BoardId",
          "value": "H3860ST9_19"
        }
      ]
    },
    {
      "data": [
        {
          "columnName": "in_NeutralColor",
          "value": "230"
        },
        {
          "columnName": "in_BoardThkMin",
          "value": "20"
        },
        {
          "columnName": "in_BoardThkMax",
          "value": "30"
        },
        {
          "columnName": "BoardId",
          "value": "H3860ST9_25"
        }
      ]
    },
    {
      "data": [
        {
          "columnName": "in_NeutralColor",
          "value": "230"
        },
        {
          "columnName": "in_BoardThkMin",
          "value": "7"
        },
        {
          "columnName": "in_BoardThkMax",
          "value": "9"
        },
        {
          "columnName": "BoardId",
          "value": "H3860ST9_8"
        }
      ]
    },
    {
      "data": [
        {
          "columnName": "in_NeutralColor",
          "value": "215"
        },
        {
          "columnName": "in_BoardThkMin",
          "value": "18"
        },
        {
          "columnName": "in_BoardThkMax",
          "value": "20"
        },
        {
          "columnName": "BoardId",
          "value": "H1715ST12_19"
        }
      ]
    },
    {
      "data": [
        {
          "columnName": "in_NeutralColor",
          "value": "215"
        },
        {
          "columnName": "in_BoardThkMin",
          "value": "7"
        },
        {
          "columnName": "in_BoardThkMax",
          "value": "9"
        },
        {
          "columnName": "BoardId",
          "value": "H1715ST12_8"
        }
      ]
    },
    {
      "data": [
        {
          "columnName": "in_NeutralColor",
          "value": "215"
        },
        {
          "columnName": "in_BoardThkMin",
          "value": "30"
        },
        {
          "columnName": "in_BoardThkMax",
          "value": "99"
        },
        {
          "columnName": "BoardId",
          "value": "H1715ST12_38"
        }
      ]
    },
    {
      "data": [
        {
          "columnName": "in_NeutralColor",
          "value": "215"
        },
        {
          "columnName": "in_BoardThkMin",
          "value": "20"
        },
        {
          "columnName": "in_BoardThkMax",
          "value": "30"
        },
        {
          "columnName": "BoardId",
          "value": "H1715ST12_25"
        }
      ]
    },
    {
      "data": [
        {
          "columnName": "in_NeutralColor",
          "value": "215"
        },
        {
          "columnName": "in_BoardThkMin",
          "value": "15"
        },
        {
          "columnName": "in_BoardThkMax",
          "value": "17"
        },
        {
          "columnName": "BoardId",
          "value": "H1715ST12_16"
        }
      ]
    },
    {
      "data": [
        {
          "columnName": "in_NeutralColor",
          "value": "214"
        },
        {
          "columnName": "in_BoardThkMin",
          "value": "18"
        },
        {
          "columnName": "in_BoardThkMax",
          "value": "20"
        },
        {
          "columnName": "BoardId",
          "value": "H3734ST9_19"
        }
      ]
    },
    {
      "data": [
        {
          "columnName": "in_NeutralColor",
          "value": "214"
        },
        {
          "columnName": "in_BoardThkMin",
          "value": "7"
        },
        {
          "columnName": "in_BoardThkMax",
          "value": "9"
        },
        {
          "columnName": "BoardId",
          "value": "H3734ST9_8"
        }
      ]
    },
    {
      "data": [
        {
          "columnName": "in_NeutralColor",
          "value": "214"
        },
        {
          "columnName": "in_BoardThkMin",
          "value": "30"
        },
        {
          "columnName": "in_BoardThkMax",
          "value": "99"
        },
        {
          "columnName": "BoardId",
          "value": "H3734ST9_38"
        }
      ]
    },
    {
      "data": [
        {
          "columnName": "in_NeutralColor",
          "value": "214"
        },
        {
          "columnName": "in_BoardThkMin",
          "value": "20"
        },
        {
          "columnName": "in_BoardThkMax",
          "value": "30"
        },
        {
          "columnName": "BoardId",
          "value": "H3734ST9_25"
        }
      ]
    },
    {
      "data": [
        {
          "columnName": "in_NeutralColor",
          "value": "214"
        },
        {
          "columnName": "in_BoardThkMin",
          "value": "15"
        },
        {
          "columnName": "in_BoardThkMax",
          "value": "17"
        },
        {
          "columnName": "BoardId",
          "value": "H3734ST9_16"
        }
      ]
    },
    {
      "data": [
        {
          "columnName": "in_NeutralColor",
          "value": "240"
        },
        {
          "columnName": "in_BoardThkMin",
          "value": "20"
        },
        {
          "columnName": "in_BoardThkMax",
          "value": "30"
        },
        {
          "columnName": "BoardId",
          "value": "H3190ST19_25"
        }
      ]
    },
    {
      "data": [
        {
          "columnName": "in_NeutralColor",
          "value": "240"
        },
        {
          "columnName": "in_BoardThkMin",
          "value": "30"
        },
        {
          "columnName": "in_BoardThkMax",
          "value": "99"
        },
        {
          "columnName": "BoardId",
          "value": "H3190ST19_38"
        }
      ]
    },
    {
      "data": [
        {
          "columnName": "in_NeutralColor",
          "value": "240"
        },
        {
          "columnName": "in_BoardThkMin",
          "value": "18"
        },
        {
          "columnName": "in_BoardThkMax",
          "value": "20"
        },
        {
          "columnName": "BoardId",
          "value": "H3190ST19_19"
        }
      ]
    },
    {
      "data": [
        {
          "columnName": "in_NeutralColor",
          "value": "240"
        },
        {
          "columnName": "in_BoardThkMin",
          "value": "7"
        },
        {
          "columnName": "in_BoardThkMax",
          "value": "9"
        },
        {
          "columnName": "BoardId",
          "value": "H3190ST19_8"
        }
      ]
    },
    {
      "data": [
        {
          "columnName": "in_NeutralColor",
          "value": "240"
        },
        {
          "columnName": "in_BoardThkMin",
          "value": "15"
        },
        {
          "columnName": "in_BoardThkMax",
          "value": "17"
        },
        {
          "columnName": "BoardId",
          "value": "H3190ST19_16"
        }
      ]
    },
    {
      "data": [
        {
          "columnName": "in_NeutralColor",
          "value": "326"
        },
        {
          "columnName": "in_BoardThkMin",
          "value": "20"
        },
        {
          "columnName": "in_BoardThkMax",
          "value": "30"
        },
        {
          "columnName": "BoardId",
          "value": "F235ST76_25"
        }
      ]
    },
    {
      "data": [
        {
          "columnName": "in_NeutralColor",
          "value": "326"
        },
        {
          "columnName": "in_BoardThkMin",
          "value": "18"
        },
        {
          "columnName": "in_BoardThkMax",
          "value": "20"
        },
        {
          "columnName": "BoardId",
          "value": "F235ST76_19"
        }
      ]
    },
    {
      "data": [
        {
          "columnName": "in_NeutralColor",
          "value": "326"
        },
        {
          "columnName": "in_BoardThkMin",
          "value": "15"
        },
        {
          "columnName": "in_BoardThkMax",
          "value": "17"
        },
        {
          "columnName": "BoardId",
          "value": "F235ST76_16"
        }
      ]
    },
    {
      "data": [
        {
          "columnName": "in_NeutralColor",
          "value": "326"
        },
        {
          "columnName": "in_BoardThkMin",
          "value": "7"
        },
        {
          "columnName": "in_BoardThkMax",
          "value": "9"
        },
        {
          "columnName": "BoardId",
          "value": "F235ST76_8"
        }
      ]
    },
    {
      "data": [
        {
          "columnName": "in_NeutralColor",
          "value": "326"
        },
        {
          "columnName": "in_BoardThkMin",
          "value": "30"
        },
        {
          "columnName": "in_BoardThkMax",
          "value": "99"
        },
        {
          "columnName": "BoardId",
          "value": "F235ST76_38"
        }
      ]
    },
    {
      "data": [
        {
          "columnName": "in_NeutralColor",
          "value": "316"
        },
        {
          "columnName": "in_BoardThkMin",
          "value": "20"
        },
        {
          "columnName": "in_BoardThkMax",
          "value": "30"
        },
        {
          "columnName": "BoardId",
          "value": "F186ST9_25"
        }
      ]
    },
    {
      "data": [
        {
          "columnName": "in_NeutralColor",
          "value": "316"
        },
        {
          "columnName": "in_BoardThkMin",
          "value": "18"
        },
        {
          "columnName": "in_BoardThkMax",
          "value": "20"
        },
        {
          "columnName": "BoardId",
          "value": "F186ST9_19"
        }
      ]
    },
    {
      "data": [
        {
          "columnName": "in_NeutralColor",
          "value": "316"
        },
        {
          "columnName": "in_BoardThkMin",
          "value": "15"
        },
        {
          "columnName": "in_BoardThkMax",
          "value": "17"
        },
        {
          "columnName": "BoardId",
          "value": "F186ST9_16"
        }
      ]
    },
    {
      "data": [
        {
          "columnName": "in_NeutralColor",
          "value": "316"
        },
        {
          "columnName": "in_BoardThkMin",
          "value": "30"
        },
        {
          "columnName": "in_BoardThkMax",
          "value": "99"
        },
        {
          "columnName": "BoardId",
          "value": "F186ST9_38"
        }
      ]
    },
    {
      "data": [
        {
          "columnName": "in_NeutralColor",
          "value": "316"
        },
        {
          "columnName": "in_BoardThkMin",
          "value": "7"
        },
        {
          "columnName": "in_BoardThkMax",
          "value": "9"
        },
        {
          "columnName": "BoardId",
          "value": "F186ST9_8"
        }
      ]
    },
    {
      "data": [
        {
          "columnName": "in_NeutralColor",
          "value": "324"
        },
        {
          "columnName": "in_BoardThkMin",
          "value": "20"
        },
        {
          "columnName": "in_BoardThkMax",
          "value": "30"
        },
        {
          "columnName": "BoardId",
          "value": "F244ST76_25"
        }
      ]
    },
    {
      "data": [
        {
          "columnName": "in_NeutralColor",
          "value": "324"
        },
        {
          "columnName": "in_BoardThkMin",
          "value": "18"
        },
        {
          "columnName": "in_BoardThkMax",
          "value": "20"
        },
        {
          "columnName": "BoardId",
          "value": "F244ST76_19"
        }
      ]
    },
    {
      "data": [
        {
          "columnName": "in_NeutralColor",
          "value": "324"
        },
        {
          "columnName": "in_BoardThkMin",
          "value": "15"
        },
        {
          "columnName": "in_BoardThkMax",
          "value": "17"
        },
        {
          "columnName": "BoardId",
          "value": "F244ST76_16"
        }
      ]
    },
    {
      "data": [
        {
          "columnName": "in_NeutralColor",
          "value": "324"
        },
        {
          "columnName": "in_BoardThkMin",
          "value": "7"
        },
        {
          "columnName": "in_BoardThkMax",
          "value": "9"
        },
        {
          "columnName": "BoardId",
          "value": "F244ST76_8"
        }
      ]
    },
    {
      "data": [
        {
          "columnName": "in_NeutralColor",
          "value": "324"
        },
        {
          "columnName": "in_BoardThkMin",
          "value": "30"
        },
        {
          "columnName": "in_BoardThkMax",
          "value": "99"
        },
        {
          "columnName": "BoardId",
          "value": "F244ST76_38"
        }
      ]
    },
    {
      "data": [
        {
          "columnName": "in_NeutralColor",
          "value": "380"
        },
        {
          "columnName": "in_BoardThkMin",
          "value": "20"
        },
        {
          "columnName": "in_BoardThkMax",
          "value": "30"
        },
        {
          "columnName": "BoardId",
          "value": "F800ST9_25"
        }
      ]
    },
    {
      "data": [
        {
          "columnName": "in_NeutralColor",
          "value": "380"
        },
        {
          "columnName": "in_BoardThkMin",
          "value": "18"
        },
        {
          "columnName": "in_BoardThkMax",
          "value": "20"
        },
        {
          "columnName": "BoardId",
          "value": "F800ST9_19"
        }
      ]
    },
    {
      "data": [
        {
          "columnName": "in_NeutralColor",
          "value": "380"
        },
        {
          "columnName": "in_BoardThkMin",
          "value": "15"
        },
        {
          "columnName": "in_BoardThkMax",
          "value": "17"
        },
        {
          "columnName": "BoardId",
          "value": "F800ST9_16"
        }
      ]
    },
    {
      "data": [
        {
          "columnName": "in_NeutralColor",
          "value": "380"
        },
        {
          "columnName": "in_BoardThkMin",
          "value": "7"
        },
        {
          "columnName": "in_BoardThkMax",
          "value": "9"
        },
        {
          "columnName": "BoardId",
          "value": "F800ST9_8"
        }
      ]
    },
    {
      "data": [
        {
          "columnName": "in_NeutralColor",
          "value": "380"
        },
        {
          "columnName": "in_BoardThkMin",
          "value": "30"
        },
        {
          "columnName": "in_BoardThkMax",
          "value": "99"
        },
        {
          "columnName": "BoardId",
          "value": "F800ST9_38"
        }
      ]
    },
    {
      "data": [
        {
          "columnName": "in_NeutralColor",
          "value": "222"
        },
        {
          "columnName": "in_BoardThkMin",
          "value": "30"
        },
        {
          "columnName": "in_BoardThkMax",
          "value": "99"
        },
        {
          "columnName": "BoardId",
          "value": "H2033ST10_38"
        }
      ]
    },
    {
      "data": [
        {
          "columnName": "in_NeutralColor",
          "value": "222"
        },
        {
          "columnName": "in_BoardThkMin",
          "value": "7"
        },
        {
          "columnName": "in_BoardThkMax",
          "value": "9"
        },
        {
          "columnName": "BoardId",
          "value": "H2033ST10_8"
        }
      ]
    },
    {
      "data": [
        {
          "columnName": "in_NeutralColor",
          "value": "222"
        },
        {
          "columnName": "in_BoardThkMin",
          "value": "20"
        },
        {
          "columnName": "in_BoardThkMax",
          "value": "30"
        },
        {
          "columnName": "BoardId",
          "value": "H2033ST10_25"
        }
      ]
    },
    {
      "data": [
        {
          "columnName": "in_NeutralColor",
          "value": "222"
        },
        {
          "columnName": "in_BoardThkMin",
          "value": "18"
        },
        {
          "columnName": "in_BoardThkMax",
          "value": "20"
        },
        {
          "columnName": "BoardId",
          "value": "H2033ST10_19"
        }
      ]
    },
    {
      "data": [
        {
          "columnName": "in_NeutralColor",
          "value": "222"
        },
        {
          "columnName": "in_BoardThkMin",
          "value": "15"
        },
        {
          "columnName": "in_BoardThkMax",
          "value": "17"
        },
        {
          "columnName": "BoardId",
          "value": "H2033ST10_16"
        }
      ]
    },
    {
      "data": [
        {
          "columnName": "in_NeutralColor",
          "value": "229"
        },
        {
          "columnName": "in_BoardThkMin",
          "value": "30"
        },
        {
          "columnName": "in_BoardThkMax",
          "value": "99"
        },
        {
          "columnName": "BoardId",
          "value": "H1199ST12_38"
        }
      ]
    },
    {
      "data": [
        {
          "columnName": "in_NeutralColor",
          "value": "229"
        },
        {
          "columnName": "in_BoardThkMin",
          "value": "7"
        },
        {
          "columnName": "in_BoardThkMax",
          "value": "9"
        },
        {
          "columnName": "BoardId",
          "value": "H1199ST12_8"
        }
      ]
    },
    {
      "data": [
        {
          "columnName": "in_NeutralColor",
          "value": "229"
        },
        {
          "columnName": "in_BoardThkMin",
          "value": "20"
        },
        {
          "columnName": "in_BoardThkMax",
          "value": "30"
        },
        {
          "columnName": "BoardId",
          "value": "H1199ST12_25"
        }
      ]
    },
    {
      "data": [
        {
          "columnName": "in_NeutralColor",
          "value": "229"
        },
        {
          "columnName": "in_BoardThkMin",
          "value": "18"
        },
        {
          "columnName": "in_BoardThkMax",
          "value": "20"
        },
        {
          "columnName": "BoardId",
          "value": "H1199ST12_19"
        }
      ]
    },
    {
      "data": [
        {
          "columnName": "in_NeutralColor",
          "value": "229"
        },
        {
          "columnName": "in_BoardThkMin",
          "value": "15"
        },
        {
          "columnName": "in_BoardThkMax",
          "value": "17"
        },
        {
          "columnName": "BoardId",
          "value": "H1199ST12_16"
        }
      ]
    },
    {
      "data": [
        {
          "columnName": "in_NeutralColor",
          "value": "178"
        },
        {
          "columnName": "in_BoardThkMin",
          "value": "15"
        },
        {
          "columnName": "in_BoardThkMax",
          "value": "17"
        },
        {
          "columnName": "BoardId",
          "value": "U708ST9_16"
        }
      ]
    },
    {
      "data": [
        {
          "columnName": "in_NeutralColor",
          "value": "178"
        },
        {
          "columnName": "in_BoardThkMin",
          "value": "18"
        },
        {
          "columnName": "in_BoardThkMax",
          "value": "20"
        },
        {
          "columnName": "BoardId",
          "value": "U708ST9_19"
        }
      ]
    },
    {
      "data": [
        {
          "columnName": "in_NeutralColor",
          "value": "178"
        },
        {
          "columnName": "in_BoardThkMin",
          "value": "20"
        },
        {
          "columnName": "in_BoardThkMax",
          "value": "30"
        },
        {
          "columnName": "BoardId",
          "value": "U708ST9_25"
        }
      ]
    },
    {
      "data": [
        {
          "columnName": "in_NeutralColor",
          "value": "178"
        },
        {
          "columnName": "in_BoardThkMin",
          "value": "30"
        },
        {
          "columnName": "in_BoardThkMax",
          "value": "99"
        },
        {
          "columnName": "BoardId",
          "value": "U708ST9_38"
        }
      ]
    },
    {
      "data": [
        {
          "columnName": "in_NeutralColor",
          "value": "178"
        },
        {
          "columnName": "in_BoardThkMin",
          "value": "7"
        },
        {
          "columnName": "in_BoardThkMax",
          "value": "9"
        },
        {
          "columnName": "BoardId",
          "value": "U708ST9_8"
        }
      ]
    }
  ]
}