{
  "variantId": "mod_RackAreaOversizeCarcaseType",
  "shortName": "Rack area oversize type",
  "variantTypeId": "Text",
  "description": "Oversize type for the carcase depth for the front module RackArea",
  "restrictionTypeId": "Internal",
  "groupName": "Front | Oversize",
  "imageId": "",
  "assignedGlobalVarId": "basic_RackAreaOversizeCarcaseType",
  "isArray": false,
  "isPosRelevant": true,
  "mainAttr": false,
  "userRight": "Master",
  "implicitRelevant": false,
  "posView": "Dropdown",
  "matrix": [],
  "selections": [
    {
      "value": "NoOversize",
      "description": "No oversize for carcase depth",
      "shortName": "NoOversize",
      "imageId": "40ef5d13-2935-44e8-866f-c5fe5ad1237f:NoOversize.jpg",
      "matrix": []
    },
    {
      "value": "FixedOversize",
      "description": "Oversize fixed value for carcase depth",
      "shortName": "FixedOversize",
      "imageId": "9bb38b51-214a-4fcb-8d30-82c66b79d066:FixedOversize.jpg",
      "matrix": []
    },
    {
      "value": "FlexibleOversize",
      "description": "Oversize based on front thickness",
      "shortName": "FlexibleOversize",
      "imageId": "7eec9d90-c66e-4651-afc6-946444145adb:FlexibleOversize.jpg",
      "matrix": []
    }
  ]
}