{
  "variantId": "mod_FrontGapHor",
  "shortName": "Horizontal",
  "variantTypeId": "Dim",
  "description": "Gap between fronts horizontal",
  "restrictionTypeId": "Public",
  "groupName": "Front | Gap",
  "imageId": "48d5b97c-bb96-4c7d-9a1c-aec76280d736:FrontGapHor.png",
  "assignedGlobalVarId": "basic_FrontGapHor",
  "isArray": false,
  "isPosRelevant": true,
  "mainAttr": false,
  "userRight": "Advanced",
  "implicitRelevant": false,
  "posView": "InputField",
  "sorting": 3,
  "matrix": [],
  "selections": []
}