{
  "variantId": "mod_HingeColor",
  "shortName": "Color",
  "variantTypeId": "Text",
  "description": "Color of the hinge",
  "restrictionTypeId": "Public",
  "groupName": "Hardware | Hinge",
  "imageId": "bcb79e5e-0a63-4c65-879f-098d2d0700fe:Hinge.jpg",
  "isArray": false,
  "isPosRelevant": true,
  "mainAttr": false,
  "userRight": "Master",
  "implicitRelevant": false,
  "posView": "ImageList",
  "matrix": [],
  "selections": [
    {
      "value": "DemoBlack",
      "description": "Demo color black",
      "shortName": "DemoBlack",
      "imageId": "3d35111f-3d6f-4df1-9794-1c7a4cbadeca:DemoBlack.jpg",
      "matrix": []
    },
    {
      "value": "DemoNickelPlated",
      "description": "Demo nickel-plated",
      "shortName": "DemoNickelPlated",
      "imageId": "f13d5d9a-0f6b-4794-aa63-38769bf3b8ef:DemoNickelPlated.jpg",
      "matrix": []
    }
  ]
}