{
  "moduleId": "mc_DrawerBox01",
  "shortName": "Drawer box",
  "configurable": false,
  "isRoot": false,
  "description": "Management of the drawer box",
  "groupName": "Hardware",
  "imageId": "a459127c-e068-4bde-bc15-b21a8490f017:Legrabox.jpg",
  "restrictionTypeId": "Internal",
  "childModules": [],
  "assignedVariants": [
    {
      "variantId": "mod_FrontHeight",
      "previewValue": "720",
      "origin": "Derived"
    },
    {
      "variantId": "mod_FrontId",
      "previewValue": "None",
      "origin": "Derived"
    },
    {
      "variantId": "mod_DrawerBoxColor",
      "previewValue": "SW",
      "origin": "Derived"
    },
    {
      "variantId": "mod_DrawerBoxDepthType",
      "previewValue": "D2",
      "origin": "Derived"
    },
    {
      "variantId": "mod_DrawerBoxHeightType",
      "previewValue": "H1",
      "origin": "Derived"
    },
    {
      "variantId": "mod_DrawerBoxOffsetDepth",
      "previewValue": "5",
      "origin": "Derived"
    },
    {
      "variantId": "mod_DrawerBoxProgram",
      "previewValue": "Pure",
      "origin": "Derived"
    },
    {
      "variantId": "mod_DrawerBoxLogic",
      "origin": "GlobalVar"
    },
    {
      "variantId": "mod_FrontWidth",
      "previewValue": "600",
      "origin": "Derived"
    },
    {
      "variantId": "mod_DrawerBoxWeightType",
      "previewValue": "Standard",
      "origin": "Derived"
    },
    {
      "variantId": "mod_ModuleName",
      "default": "mc_DrawerBox01",
      "origin": "Fixed"
    },
    {
      "variantId": "mod_DrawerBoxDesign",
      "previewValue": "Legrabox",
      "origin": "Derived"
    },
    {
      "variantId": "mod_Depth",
      "previewValue": "575",
      "origin": "Derived"
    },
    {
      "variantId": "mod_Width",
      "previewValue": "600",
      "origin": "Derived"
    },
    {
      "variantId": "mod_Height",
      "default": "0",
      "origin": "Default"
    },
    {
      "variantId": "mod_HardwareColor",
      "previewValue": "LightColor",
      "origin": "Derived"
    },
    {
      "variantId": "mod_TypeElement",
      "previewValue": "BaseUnit",
      "origin": "Derived"
    },
    {
      "variantId": "mod_OpeningType",
      "previewValue": "Handle",
      "origin": "Derived"
    },
    {
      "variantId": "mod_FrontProgram",
      "previewValue": "Demoprogram1",
      "origin": "Derived"
    },
    {
      "variantId": "mod_ParentName",
      "previewValue": "None",
      "origin": "Derived"
    },
    {
      "variantId": "mod_PartgroupDrawerWeight",
      "default": "0",
      "origin": "Default"
    },
    {
      "variantId": "mod_CarcaseProgram",
      "previewValue": "Classic",
      "origin": "Derived"
    },
    {
      "variantId": "mod_GrainLogic",
      "previewValue": "Library",
      "origin": "Derived"
    }
  ],
  "assignedParts": [
    {
      "partCode": "part_DrawerShelfbtm"
    },
    {
      "partCode": "part_DrawerBackwallWood"
    },
    {
      "partCode": "part_DrawerBackwallSteel"
    },
    {
      "partCode": "part_DrawerBox"
    },
    {
      "partCode": "part_DrawerSideLeft"
    },
    {
      "partCode": "part_DrawerSideRight"
    },
    {
      "partCode": "part_DrawerBoxDrilling"
    },
    {
      "partCode": "part_DrawerBoxBom"
    },
    {
      "partCode": "part_DrawerSlideLeft"
    },
    {
      "partCode": "part_DrawerSlideRight"
    },
    {
      "partCode": "part_DrawerFrontConnector"
    },
    {
      "partCode": "part_DrawerShelfbtmConnector"
    },
    {
      "partCode": "part_DrawerShelfbtmConnectorDrilling"
    },
    {
      "partCode": "part_DrawerBoxSynchronization"
    }
  ],
  "assignedCustomTables": [],
  "assignedFunctions": [
    {
      "functionId": "process_Drawerbox"
    }
  ]
}