{
  "variantId": "mod_Color",
  "shortName": "Decor",
  "variantTypeId": "Text",
  "description": "Color of the panels",
  "restrictionTypeId": "Public",
  "groupName": "Global",
  "imageId": "aa502bb7-82ef-4229-bcaf-106437fe15b8:mod_Color.jpg",
  "isArray": false,
  "isPosRelevant": true,
  "mainAttr": true,
  "userRight": "Simple",
  "implicitRelevant": false,
  "posView": "ImageList",
  "matrix": [
    {
      "id": "GrainGroupId",
      "type": "Text",
      "shortName": "Grain",
      "default": "NoGrain"
    }
  ],
  "selections": [
    {
      "value": "MDF",
      "description": "MDF board",
      "shortName": "MDF board",
      "imageId": "83de6e70-6bbb-4b7d-b31e-4faf20999be4:MDF_P.png",
      "matrix": [
        {
          "id": "GrainGroupId",
          "value": "NoGrain"
        }
      ]
    },
    {
      "value": "FPY",
      "description": "Chip board",
      "shortName": "Chip board",
      "imageId": "f86ca5f5-601b-4cf0-9cb1-15079d047ce5:CB.png",
      "matrix": [
        {
          "id": "GrainGroupId",
          "value": "NoGrain"
        }
      ]
    },
    {
      "value": "Acryl",
      "description": "Acryl glass",
      "shortName": "Acryl glass",
      "imageId": "59531254-430e-4488-b16c-c243f0743fe7:SatinGlass.jpg",
      "matrix": [
        {
          "id": "GrainGroupId",
          "value": "NoGrain"
        }
      ]
    },
    {
      "value": "egger_f186_st9",
      "description": "Egger: Light Grey Chicago Concrete (F186 ST9)",
      "shortName": "Light Grey Chicago Concrete (F186 ST9)",
      "imageId": "6bbce4de-e4cc-4833-a685-93af8b135957:egger_f186_st9.png",
      "matrix": [
        {
          "id": "GrainGroupId",
          "value": "Grain"
        }
      ]
    },
    {
      "value": "egger_f235_st76",
      "description": "Egger: Scivaro Slate (F235 ST76)",
      "shortName": "Scivaro Slate (F235 ST76)",
      "imageId": "d8b5adbd-6793-40e2-8c27-cde22af85764:egger_f235_st76.png",
      "matrix": [
        {
          "id": "GrainGroupId",
          "value": "Grain"
        }
      ]
    },
    {
      "value": "egger_f244_st76",
      "description": "Egger: Anthracite Candela Marble (F244 ST76)",
      "shortName": "Anthracite Candela Marble (F244 ST76)",
      "imageId": "30384df4-0c7c-4a0a-9bad-fc49ad26f390:egger_f244_st76.png",
      "matrix": [
        {
          "id": "GrainGroupId",
          "value": "Grain"
        }
      ]
    },
    {
      "value": "egger_f800_st9",
      "description": "Egger: Crystal Marble (F800 ST9)",
      "shortName": "Crystal Marble (F800 ST9)",
      "imageId": "00c43ed9-c20b-423c-961a-438f79562c9e:egger_f800_st9.png",
      "matrix": [
        {
          "id": "GrainGroupId",
          "value": "Grain"
        }
      ]
    },
    {
      "value": "egger_h1199_st12",
      "description": "Egger: Black-Brown Thermo Oak (H1199 ST12)",
      "shortName": "Black-Brown Thermo Oak (H1199 ST12)",
      "imageId": "b92caa2e-7e10-4a2b-a9d6-be28100b3084:egger_h1199_st12.png",
      "matrix": [
        {
          "id": "GrainGroupId",
          "value": "Grain"
        }
      ]
    },
    {
      "value": "egger_h1715_st12",
      "description": "Egger: Parona Walnut (H1715 ST12)",
      "shortName": "Parona Walnut (H1715 ST12)",
      "imageId": "713503cb-b052-461c-90ee-459b311bcbb5:egger_h1715_st12.png",
      "matrix": [
        {
          "id": "GrainGroupId",
          "value": "Grain"
        }
      ]
    },
    {
      "value": "egger_h2033_st10",
      "description": "Egger: Dark Hunton Oak (H2033 ST10)",
      "shortName": "Dark Hunton Oak (H2033 ST10)",
      "imageId": "02575a5a-73cc-47a5-9726-483343e8fe1b:egger_h2033_st10.png",
      "matrix": [
        {
          "id": "GrainGroupId",
          "value": "Grain"
        }
      ]
    },
    {
      "value": "egger_h3190_st19",
      "description": "Egger: Anthracite Fineline Metallic (H3190 ST19)",
      "shortName": "Anthracite Fineline Metallic (H3190 ST19)",
      "imageId": "7a901ff6-0257-42a4-9216-af02a6205751:egger_h3190_st19.png",
      "matrix": [
        {
          "id": "GrainGroupId",
          "value": "Grain"
        }
      ]
    },
    {
      "value": "egger_h3734_st9",
      "description": "Egger: Natural Dijon Walnut (H3734 ST9)",
      "shortName": "Natural Dijon Walnut (H3734 ST9)",
      "imageId": "3b17ff33-ffd8-4971-ba4c-2d6a6c300ff0:egger_h3734_st9.png",
      "matrix": [
        {
          "id": "GrainGroupId",
          "value": "Grain"
        }
      ]
    },
    {
      "value": "egger_h3860_st9",
      "description": "Egger: Champagne Hard Maple (H3860 ST9)",
      "shortName": "Champagne Hard Maple (H3860 ST9)",
      "imageId": "f2527475-cfe7-42b2-a624-2c2ce90d98ce:egger_h3860_st9.png",
      "matrix": [
        {
          "id": "GrainGroupId",
          "value": "Grain"
        }
      ]
    },
    {
      "value": "egger_u502_st9",
      "description": "Egger: Misty Blue (U502 ST9)",
      "shortName": "Misty Blue (U502 ST9)",
      "imageId": "2c918d1a-958c-4156-80d5-a3795a1041b5:egger_u502_st9.png",
      "matrix": [
        {
          "id": "GrainGroupId",
          "value": "NoGrain"
        }
      ]
    },
    {
      "value": "egger_u575_st9",
      "description": "Egger: Cosmos Blue (U575 ST9)",
      "shortName": "Cosmos Blue (U575 ST9)",
      "imageId": "d7d13b24-1179-4287-8e33-361082baf0a7:egger_u575_st9.png",
      "matrix": [
        {
          "id": "GrainGroupId",
          "value": "NoGrain"
        }
      ]
    },
    {
      "value": "egger_u640_st9",
      "description": "Egger: Olive Green (U640 ST9)",
      "shortName": "Olive Green (U640 ST9)",
      "imageId": "516abcfd-c119-48aa-9f89-e5bb97510b53:egger_u640_st9.png",
      "matrix": [
        {
          "id": "GrainGroupId",
          "value": "NoGrain"
        }
      ]
    },
    {
      "value": "egger_u645_st9",
      "description": "Egger: Agave Green (U645 ST9)",
      "shortName": "Agave Green (U645 ST9)",
      "imageId": "548f0d1a-1b5f-42a3-8e09-b3b47d032bfc:egger_u645_st9.png",
      "matrix": [
        {
          "id": "GrainGroupId",
          "value": "NoGrain"
        }
      ]
    },
    {
      "value": "egger_u708_pg",
      "description": "Egger: Light Grey (U708 PG)",
      "shortName": "Light Grey (U708 PG)",
      "imageId": "03c42d61-04d6-4478-9bae-4b3db573602f:egger_u708_pg.png",
      "matrix": [
        {
          "id": "GrainGroupId",
          "value": "NoGrain"
        }
      ]
    },
    {
      "value": "egger_u708_pm",
      "description": "Egger: Light Grey (U708 PM)",
      "shortName": "Light Grey (U708 PM)",
      "imageId": "fbf1722e-12a7-450a-b355-135b14537b09:egger_u708_pm.png",
      "matrix": [
        {
          "id": "GrainGroupId",
          "value": "NoGrain"
        }
      ]
    },
    {
      "value": "egger_u708_st9",
      "description": "Egger: Light Grey (U708 ST9)",
      "shortName": "Light Grey (U708 ST9)",
      "imageId": "69924419-a877-41f0-9bc6-7889ba83dc93:egger_u708_st9.png",
      "matrix": [
        {
          "id": "GrainGroupId",
          "value": "NoGrain"
        }
      ]
    },
    {
      "value": "egger_u999_st12",
      "description": "Egger: Black (U999 ST12)",
      "shortName": "Black (U999 ST12)",
      "imageId": "ecf331f8-1f0f-41bf-970e-77744d27fd3b:egger_u999_st12.png",
      "matrix": [
        {
          "id": "GrainGroupId",
          "value": "NoGrain"
        }
      ]
    },
    {
      "value": "egger_u999_st19",
      "description": "Egger: Black (U999 ST19)",
      "shortName": "Black (U999 ST19)",
      "imageId": "4f424c75-5ca5-4e30-9462-4bfaabb457ee:egger_u999_st19.png",
      "matrix": [
        {
          "id": "GrainGroupId",
          "value": "NoGrain"
        }
      ]
    },
    {
      "value": "egger_u999_st20",
      "description": "Egger: Black (U999 ST20)",
      "shortName": "Black (U999 ST20)",
      "imageId": "f2697a82-9e54-4b92-a9f3-ce37d938c8f7:egger_u999_st20.png",
      "matrix": [
        {
          "id": "GrainGroupId",
          "value": "NoGrain"
        }
      ]
    },
    {
      "value": "egger_u999_st7",
      "description": "Egger: Black (U999 ST7)",
      "shortName": "Black (U999 ST7)",
      "imageId": "592ac2de-3239-4b8a-b66c-991d14c8361a:egger_u999_st7.png",
      "matrix": [
        {
          "id": "GrainGroupId",
          "value": "NoGrain"
        }
      ]
    },
    {
      "value": "egger_w1000_pm",
      "description": "Egger: Premium White (W1000 PM)",
      "shortName": "Premium White (W1000 PM)",
      "imageId": "ccc0a6f5-e1bd-4b18-92f3-b073e3aa70fe:egger_w1000_pm.png",
      "matrix": [
        {
          "id": "GrainGroupId",
          "value": "NoGrain"
        }
      ]
    },
    {
      "value": "egger_w1000_st19",
      "description": "Egger: Premium White (W1000 ST19)",
      "shortName": "Premium White (W1000 ST19)",
      "imageId": "1365b12a-617b-4faa-ab07-81192b0f8962:egger_w1000_st19.png",
      "matrix": [
        {
          "id": "GrainGroupId",
          "value": "NoGrain"
        }
      ]
    },
    {
      "value": "egger_w1000_st38",
      "description": "Egger: Premium White (W1000 ST38)",
      "shortName": "Premium White (W1000 ST38)",
      "imageId": "2cff9d23-179f-4b5a-8728-e45300c600a5:egger_w1000_st38.png",
      "matrix": [
        {
          "id": "GrainGroupId",
          "value": "NoGrain"
        }
      ]
    },
    {
      "value": "egger_w1000_st9",
      "description": "Egger: Premium White (W1000 ST9)",
      "shortName": "Premium White (W1000 ST9)",
      "imageId": "d2d3953a-4595-4404-8be7-c083c8997425:egger_w1000_st9.png",
      "matrix": [
        {
          "id": "GrainGroupId",
          "value": "NoGrain"
        }
      ]
    },
    {
      "value": "egger_w980_sm",
      "description": "Egger: Platinum White (W980 SM)",
      "shortName": "Platinum White (W980 SM)",
      "imageId": "a230e0d2-830b-4a4e-b09e-2f1d9dc2d077:egger_w980_sm.png",
      "matrix": [
        {
          "id": "GrainGroupId",
          "value": "NoGrain"
        }
      ]
    },
    {
      "value": "egger_w980_st7",
      "description": "Egger: Platinum White (W980 ST7)",
      "shortName": "Platinum White (W980 ST7)",
      "imageId": "16afddf3-7d53-4ebe-b3f6-381804f45ad4:egger_w980_st7.png",
      "matrix": [
        {
          "id": "GrainGroupId",
          "value": "NoGrain"
        }
      ]
    },
    {
      "value": "kronospan_0112_pe",
      "description": "Kronospan: Stone Grey (0112 PE)",
      "shortName": "Stone Grey (0112 PE)",
      "imageId": "5ebafe1c-1f8d-41ba-8887-b5918f256347:kronospan_0112_pe.png",
      "matrix": [
        {
          "id": "GrainGroupId",
          "value": "NoGrain"
        }
      ]
    },
    {
      "value": "kronospan_0125_bs",
      "description": "Kronospan: Royal Blue (0125 BS)",
      "shortName": "Royal Blue (0125 BS)",
      "imageId": "62860950-9aed-4367-b559-c4ead661b939:kronospan_0125_bs.png",
      "matrix": [
        {
          "id": "GrainGroupId",
          "value": "NoGrain"
        }
      ]
    },
    {
      "value": "kronospan_0164_pd",
      "description": "Kronospan: Anthracite (0164 PD)",
      "shortName": "Anthracite (0164 PD)",
      "imageId": "ffad9c6f-5322-4d43-9f0c-0be49cc5cb65:kronospan_0164_pd.png",
      "matrix": [
        {
          "id": "GrainGroupId",
          "value": "NoGrain"
        }
      ]
    },
    {
      "value": "kronospan_0164_pe",
      "description": "Kronospan: Anthracite (0164 PE)",
      "shortName": "Anthracite (0164 PE)",
      "imageId": "fec9ef9a-6b0e-4dcd-b4eb-3a7b1509ba0b:kronospan_0164_pe.png",
      "matrix": [
        {
          "id": "GrainGroupId",
          "value": "NoGrain"
        }
      ]
    },
    {
      "value": "kronospan_0244_su",
      "description": "Kronospan: Petrol (0244 SU)",
      "shortName": "Petrol (0244 SU)",
      "imageId": "92e0aeaa-6997-47cc-9732-0016a89751b3:kronospan_0244_su.png",
      "matrix": [
        {
          "id": "GrainGroupId",
          "value": "NoGrain"
        }
      ]
    },
    {
      "value": "kronospan_0375_bs",
      "description": "Kronospan: Maple (0375 BS)",
      "shortName": "Maple (0375 BS)",
      "imageId": "82fb923c-1581-488c-9c38-de1b56a87eeb:kronospan_0375_bs.png",
      "matrix": [
        {
          "id": "GrainGroupId",
          "value": "Grain"
        }
      ]
    },
    {
      "value": "kronospan_0854_bs",
      "description": "Kronospan: Wenge (0854 BS)",
      "shortName": "Wenge (0854 BS)",
      "imageId": "b5a9db08-2bb3-4498-8b17-39eadaa07768:kronospan_0854_bs.png",
      "matrix": [
        {
          "id": "GrainGroupId",
          "value": "Grain"
        }
      ]
    },
    {
      "value": "kronospan_4299_su",
      "description": "Kronospan: Dark Atelier (4299 SU)",
      "shortName": "Dark Atelier (4299 SU)",
      "imageId": "95f2b6ec-be71-4306-be12-b6ee70591433:kronospan_4299_su.png",
      "matrix": [
        {
          "id": "GrainGroupId",
          "value": "Grain"
        }
      ]
    },
    {
      "value": "kronospan_8685_pd",
      "description": "Kronospan: Snow White (8685 PD)",
      "shortName": "Snow White (8685 PD)",
      "imageId": "4d2e3569-8ad1-4f97-b31a-957cad68ca84:kronospan_8685_pd.png",
      "matrix": [
        {
          "id": "GrainGroupId",
          "value": "NoGrain"
        }
      ]
    },
    {
      "value": "kronospan_8953_su",
      "description": "Kronospan: Tiepolo Walnut (8953 SU)",
      "shortName": "Tiepolo Walnut (8953 SU)",
      "imageId": "f91886e6-a0d1-4019-b2f4-92928c9d33a2:kronospan_8953_su.png",
      "matrix": [
        {
          "id": "GrainGroupId",
          "value": "Grain"
        }
      ]
    },
    {
      "value": "kronospan_k016_su",
      "description": "Kronospan: Carbon Marine Wood (K016 SU)",
      "shortName": "Carbon Marine Wood (K016 SU)",
      "imageId": "a9a51589-52fc-4a58-9098-ec5daa9566c4:kronospan_k016_su.png",
      "matrix": [
        {
          "id": "GrainGroupId",
          "value": "Grain"
        }
      ]
    },
    {
      "value": "kronospan_k023_bs",
      "description": "Kronospan: Venato (K023 BS)",
      "shortName": "Venato (K023 BS)",
      "imageId": "c8495158-d146-479d-86bb-d401d9af0d7e:kronospan_k023_bs.png",
      "matrix": [
        {
          "id": "GrainGroupId",
          "value": "Grain"
        }
      ]
    },
    {
      "value": "kronospan_k098_su",
      "description": "Kronospan: Ceramic Red (K098 SU)",
      "shortName": "Ceramic Red (K098 SU)",
      "imageId": "9b616a32-4987-4e5f-b39a-f4db820841b3:kronospan_k098_su.png",
      "matrix": [
        {
          "id": "GrainGroupId",
          "value": "NoGrain"
        }
      ]
    },
    {
      "value": "kronospan_k350_rt",
      "description": "Kronospan: Concrete Flow (K350 RT)",
      "shortName": "Concrete Flow (K350 RT)",
      "imageId": "8675afd1-2ab9-47b6-a11c-410938002137:kronospan_k350_rt.png",
      "matrix": [
        {
          "id": "GrainGroupId",
          "value": "Grain"
        }
      ]
    },
    {
      "value": "kronospan_k351_rt",
      "description": "Kronospan: Rusty Flow (K351 RT)",
      "shortName": "Rusty Flow (K351 RT)",
      "imageId": "6f8ab2e7-0ea8-4d1c-b09b-c92ea5610c73:kronospan_k351_rt.png",
      "matrix": [
        {
          "id": "GrainGroupId",
          "value": "Grain"
        }
      ]
    },
    {
      "value": "kronospan_k353_bs",
      "description": "Kronospan: Charcoal Flow (K353 BS)",
      "shortName": "Charcoal Flow (K353 BS)",
      "imageId": "01f13fae-1300-4e16-96f3-53be6017a129:kronospan_k353_bs.png",
      "matrix": [
        {
          "id": "GrainGroupId",
          "value": "Grain"
        }
      ]
    },
    {
      "value": "kronospan_k366_pw",
      "description": "Kronospan: Fossil Evoke Oak (K366 PW)",
      "shortName": "Fossil Evoke Oak (K366 PW)",
      "imageId": "1ae48ae2-d732-49e8-a888-cc2798db4560:kronospan_k366_pw.png",
      "matrix": [
        {
          "id": "GrainGroupId",
          "value": "Grain"
        }
      ]
    },
    {
      "value": "kronospan_k409_bs",
      "description": "Kronospan: Black Pietra Marble (K409 BS)",
      "shortName": "Black Pietra Marble (K409 BS)",
      "imageId": "94207671-16cc-47f2-9a91-49c62d134c15:kronospan_k409_bs.png",
      "matrix": [
        {
          "id": "GrainGroupId",
          "value": "Grain"
        }
      ]
    },
    {
      "value": "kronospan_k517_su",
      "description": "Kronospan: Azure Blue (K517 SU)",
      "shortName": "Azure Blue (K517 SU)",
      "imageId": "52957a24-5b06-4a95-8266-da08b80b8064:kronospan_k517_su.png",
      "matrix": [
        {
          "id": "GrainGroupId",
          "value": "NoGrain"
        }
      ]
    },
    {
      "value": "kronospan_k530_hu",
      "description": "Kronospan: Amaretto Hudson Oak (K530 HU)",
      "shortName": "Amaretto Hudson Oak (K530 HU)",
      "imageId": "9931fa7c-2964-4a57-b27c-da2e4bb02bcb:kronospan_k530_hu.png",
      "matrix": [
        {
          "id": "GrainGroupId",
          "value": "Grain"
        }
      ]
    },
    {
      "value": "kronospan_k532_ad",
      "description": "Kronospan: Flamed Arvadonna Chestnut (K532 AD)",
      "shortName": "Flamed Arvadonna Chestnut (K532 AD)",
      "imageId": "47f96240-c74f-4423-a72b-94ee339a437b:kronospan_k532_ad.png",
      "matrix": [
        {
          "id": "GrainGroupId",
          "value": "Grain"
        }
      ]
    },
    {
      "value": "kronospan_k534_ad",
      "description": "Kronospan: Charcoal Arvadonna Chestnut (K534 AD)",
      "shortName": "Charcoal Arvadonna Chestnut (K534 AD)",
      "imageId": "d3b5c836-06aa-4baa-9d35-f7d7dbb9a015:kronospan_k534_ad.png",
      "matrix": [
        {
          "id": "GrainGroupId",
          "value": "Grain"
        }
      ]
    },
    {
      "value": "kronospan_k682_pd",
      "description": "Kronospan: Alpaca (K682 PD)",
      "shortName": "Alpaca (K682 PD)",
      "imageId": "8824ffbb-faa0-4e37-8d0d-4bc1b05fa60c:kronospan_k682_pd.png",
      "matrix": [
        {
          "id": "GrainGroupId",
          "value": "NoGrain"
        }
      ]
    },
    {
      "value": "pfleiderer_f76028_fg",
      "description": "Pfleiderer: Rabac (F76028 FG)",
      "shortName": "Rabac (F76028 FG)",
      "imageId": "dcdff48a-7425-48f9-b617-8dd888b0502b:pfleiderer_f76028_fg.png",
      "matrix": [
        {
          "id": "GrainGroupId",
          "value": "Grain"
        }
      ]
    },
    {
      "value": "pfleiderer_f76110_pa",
      "description": "Pfleiderer: Kito Bronze (F76110 PA)",
      "shortName": "Kito Bronze (F76110 PA)",
      "imageId": "3d49eb68-b22d-4cd3-8ec0-4d596d8cc496:pfleiderer_F76110_PA.png",
      "matrix": [
        {
          "id": "GrainGroupId",
          "value": "Grain"
        }
      ]
    },
    {
      "value": "pfleiderer_f76110_sd",
      "description": "Pfleiderer: Kito Bronze (F76110 SD)",
      "shortName": "Kito Bronze (F76110 SD)",
      "imageId": "32725995-4b36-4789-b071-b80a376bb465:pfleiderer_f76110_sd.png",
      "matrix": [
        {
          "id": "GrainGroupId",
          "value": "Grain"
        }
      ]
    },
    {
      "value": "pfleiderer_r20391_nw",
      "description": "Pfleiderer: Nutmeg Bijoux Oak (R20391 NW)",
      "shortName": "Nutmeg Bijoux Oak (R20391 NW)",
      "imageId": "a7c37ec6-391c-4ff4-9552-8b15239ceb0f:pfleiderer_r20391_nw.png",
      "matrix": [
        {
          "id": "GrainGroupId",
          "value": "Grain"
        }
      ]
    },
    {
      "value": "pfleiderer_r27001_vv",
      "description": "Pfleiderer: Royal Maple (R27001 VV)",
      "shortName": "Royal Maple (R27001 VV)",
      "imageId": "7bb1afbe-b7c1-4e76-8600-93de03cb889c:pfleiderer_r27001_vv.png",
      "matrix": [
        {
          "id": "GrainGroupId",
          "value": "Grain"
        }
      ]
    },
    {
      "value": "pfleiderer_r50030_fl",
      "description": "Pfleiderer: Spain Olive Light (R50030 FL)",
      "shortName": "Spain Olive Light (R50030 FL)",
      "imageId": "9931fa7c-2964-4a57-b27c-da2e4bb02bcb:kronospan_k530_hu.png",
      "matrix": [
        {
          "id": "GrainGroupId",
          "value": "Grain"
        }
      ]
    },
    {
      "value": "pfleiderer_r55004_du",
      "description": "Pfleiderer: Ponderosa Pine (R55004 DU)",
      "shortName": "Ponderosa Pine (R55004 DU)",
      "imageId": "2b0b56bc-0290-409b-82e3-09bfdd53476b:pfleiderer_r55004_du.png",
      "matrix": [
        {
          "id": "GrainGroupId",
          "value": "Grain"
        }
      ]
    },
    {
      "value": "pfleiderer_s61045_ca",
      "description": "Pfleiderer: Elba (S61045 CA)",
      "shortName": "Elba (S61045 CA)",
      "imageId": "9923fb2d-d93e-4c32-93b5-305eafc11dba:pfleiderer_S61045_CA.png",
      "matrix": [
        {
          "id": "GrainGroupId",
          "value": "Grain"
        }
      ]
    },
    {
      "value": "pfleiderer_s63068_sm",
      "description": "Pfleiderer: Caviar Green (S63068 SM)",
      "shortName": "Caviar Green (S63068 SM)",
      "imageId": "bb5a6543-1f58-47b4-84c8-b963a729e212:pfleiderer_s63068_sm.png",
      "matrix": [
        {
          "id": "GrainGroupId",
          "value": "Grain"
        }
      ]
    },
    {
      "value": "pfleiderer_s63088_ms",
      "description": "Pfleiderer: Marquina Grey (S63088 MS)",
      "shortName": "Marquina Grey (S63088 MS)",
      "imageId": "7e182e42-6d4e-4f58-942a-a3f2aa24a553:pfleiderer_S63088_MS.png",
      "matrix": [
        {
          "id": "GrainGroupId",
          "value": "Grain"
        }
      ]
    },
    {
      "value": "pfleiderer_u11027_sd",
      "description": "Pfleiderer: Icy White (U11027 SD)",
      "shortName": "Icy White (U11027 SD)",
      "imageId": "15beadc8-e75e-4c83-a651-32aa70106f8a:pfleiderer_u11027_sd.png",
      "matrix": [
        {
          "id": "GrainGroupId",
          "value": "NoGrain"
        }
      ]
    },
    {
      "value": "pfleiderer_u11509_sd",
      "description": "Pfleiderer: Magnolia (U11509 SD)",
      "shortName": "Magnolia (U11509 SD)",
      "imageId": "9db472e4-86cb-490f-949a-1410c61bb331:pfleiderer_u11509_sd.png",
      "matrix": [
        {
          "id": "GrainGroupId",
          "value": "NoGrain"
        }
      ]
    },
    {
      "value": "pfleiderer_u16009_sd",
      "description": "Pfleiderer: Golden Orange (U16009 SD)",
      "shortName": "Golden Orange (U16009 SD)",
      "imageId": "51ba5653-8fd3-41ec-83cb-88f7ab1d359e:pfleiderer_u16009_sd.png",
      "matrix": [
        {
          "id": "GrainGroupId",
          "value": "NoGrain"
        }
      ]
    },
    {
      "value": "pfleiderer_u17141_sd",
      "description": "Pfleiderer: Orchidea (U17141 SD)",
      "shortName": "Orchidea (U17141 SD)",
      "imageId": "d9286cb8-08bf-41ca-8209-911e09ac8d8e:pfleiderer_u17141_sd.png",
      "matrix": [
        {
          "id": "GrainGroupId",
          "value": "NoGrain"
        }
      ]
    },
    {
      "value": "pfleiderer_u18576_sd",
      "description": "Pfleiderer: Ocean (U18576 SD)",
      "shortName": "Ocean (U18576 SD)",
      "imageId": "645ed8bc-eb66-4a6a-8681-17349ac610bb:pfleiderer_u18576_sd.png",
      "matrix": [
        {
          "id": "GrainGroupId",
          "value": "NoGrain"
        }
      ]
    },
    {
      "value": "pfleiderer_u19502_sd",
      "description": "Pfleiderer: Lime (U19502 SD)",
      "shortName": "Lime (U19502 SD)",
      "imageId": "ae3d0d64-67b6-4cbf-895c-72f718cee48c:pfleiderer_u19502_sd.png",
      "matrix": [
        {
          "id": "GrainGroupId",
          "value": "NoGrain"
        }
      ]
    }
  ]
}