{
  "variantId": "mod_Program",
  "shortName": "Program",
  "variantTypeId": "Text",
  "description": "Material category of the panels",
  "restrictionTypeId": "Public",
  "groupName": "Global",
  "imageId": "c195a156-eab2-4ebb-bbcf-d6854bc71c89:Program.jpg",
  "isArray": false,
  "isPosRelevant": true,
  "mainAttr": false,
  "userRight": "Master",
  "implicitRelevant": false,
  "matrix": [],
  "selections": [
    {
      "value": "Nature",
      "description": "Program in nature colors with vertical grain",
      "shortName": "Nature",
      "imageId": "46d60e21-f08a-49c3-8d14-deef4d1cafa3:Nature.jpg",
      "matrix": []
    },
    {
      "value": "Classic",
      "description": "Program in single colors",
      "shortName": "Classic",
      "imageId": "a8a673b2-0fe7-4f9f-85ed-1b17399ce143:Classic.jpg",
      "matrix": []
    }
  ]
}