{
  "variantId": "mod_HandleActivated",
  "shortName": "Handle activated",
  "variantTypeId": "Text",
  "description": "Activate the handle on the fronts if there are splitted fronts",
  "restrictionTypeId": "Internal",
  "groupName": "FrontOpening | Handle",
  "imageId": "5f5096b6-e7db-45d4-836b-68b0e2f5e863:HandleActivated.png",
  "isArray": false,
  "isPosRelevant": true,
  "mainAttr": false,
  "userRight": "Master",
  "implicitRelevant": false,
  "posView": "Dropdown",
  "matrix": [],
  "selections": [
    {
      "value": "All",
      "description": "All",
      "shortName": "All",
      "matrix": []
    },
    {
      "value": "Top",
      "description": "Top",
      "shortName": "Top",
      "matrix": []
    },
    {
      "value": "Bottom",
      "description": "Bottom",
      "shortName": "Bottom",
      "matrix": []
    }
  ]
}