{
  "variantId": "mod_HangerPosY",
  "shortName": "Hanger position y",
  "variantTypeId": "Text",
  "description": "Position in height of the hanger",
  "restrictionTypeId": "Internal",
  "groupName": "Hardware | Hanger",
  "imageId": "62ae2d76-42a8-4fd7-8468-95f118a0a1ac:Hanger_POSY.jpg",
  "isArray": false,
  "isPosRelevant": true,
  "mainAttr": false,
  "userRight": "Master",
  "implicitRelevant": false,
  "posView": "InputField",
  "matrix": [],
  "selections": [
    {
      "value": "Automatic",
      "description": "Automatic Vertical Position",
      "shortName": "Automatic",
      "imageId": "9cdbd4f6-4c2a-4e49-8518-a7f81ccb5c8e:Automatic.png",
      "matrix": []
    },
    {
      "value": "Manual",
      "description": "Manual Vertical Position",
      "shortName": "Manual",
      "imageId": "ffa33627-6cdc-4b76-9f6a-a7abfa594418:Manual.png",
      "matrix": []
    },
    {
      "value": "Top",
      "description": "Top Position",
      "shortName": "Top",
      "imageId": "c0531c79-0c1b-435d-b8fc-3ff239b989da:Top_New.png",
      "matrix": []
    },
    {
      "value": "Middle",
      "description": "Middle Position",
      "shortName": "Middle",
      "imageId": "5072037b-103e-42e5-8a18-96e730c0c437:Middle_New.png",
      "matrix": []
    }
  ]
}