[
  {
    "tableName": "tab_DishwasherMapping",
    "columnId": "in_DishwasherId",
    "enumsJson": [
      {
        "value": "SN55ZS07CE",
        "imageId": "cda6e3e2-72c7-47ed-8181-ebb18b757be5:SN55ZS07CE.jpg"
      },
      {
        "value": "SN87TX02CE",
        "imageId": "6ab916cb-8a42-4a3f-b478-34abdc2f8aa8:SN87TX02CE.jpg"
      },
      {
        "value": "SR55ZS10ME",
        "imageId": "849930d0-1cb6-4629-956a-c41bc8e62b72:SR55ZS10ME.jpg"
      },
      {
        "value": "SR65YX08ME",
        "imageId": "18490f77-86d4-47a1-9561-2cf761fb9e24:SR65YX08ME.jpg"
      }
    ]
  },
  {
    "tableName": "tab_DishwasherMapping",
    "columnId": "in_Supplier",
    "enumsJson": [
      {
        "value": "Siemens",
        "description": "Siemens",
        "imageId": "8ad947dc-433f-461f-9c26-aa0b77e05837:Simens.jpg"
      },
      {
        "value": "None",
        "description": "None"
      }
    ]
  }
]